saviour/UTEC/Arqui/lab/lab_03/ejercicio_1/TFF/Behavioral/tff.v
module tff(prn, t, clk, clrn, q, nq);

	input prn, t, clk, clrn;
	output q ,nq;
	wire w1, w2, w3, w4, w5, w6;

	//Tlatch master

        assign w1 = ~(t & ~clk & nq & clrn);
        assign w2 = ~(t & prn & ~clk & q);

	assign w3 = ~(w1 & prn & w4);
	assign w4 = ~(w3 & w2 & clrn);

	//Dlatch slave
	
	assign w5 = ~(w3 & clrn & clk);
	assign w6 = ~(w4 & prn & clk);

	//output
	assign q = ~(w5 & prn & nq);
	assign nq = ~(w6 & clrn & q);

endmodule

saviour/UTEC/Arqui/lab/lab_03/ejercicio_1/TFF/Behavioral/tff_tb.v
`timescale 1ns/1ns
module tff_tb;
        reg prn, t, clk, clrn;

        wire q, nq;

        tff tf1 (prn, t, clk, clrn, q, nq);
        initial begin
        	prn = 0;
                t = 1;
		clk = 1;
		clrn = 1;

                $display("time\tprn\tt\tclk\tclrn\tq\tnq"); $monitor("%2d:\t%b\t%b\t%b\t%b\t%b\t%b",$time, prn, t, clk, clrn, q, nq);
                #23 $finish;
        end

        always #1 clk = !clk;

        initial begin
                $dumpfile("tff.vcd");
                $dumpvars;
        end

        endmodule

saviour/UTEC/Arqui/lab/lab_03/ejercicio_1/TFF/Behavioral/tff.vcd
$date
	Thu May 14 10:13:20 2020
$end
$version
	Icarus Verilog
$end
$timescale
	1ns
$end
$scope module tff_tb $end
$var wire 1 ! q $end
$var wire 1 " nq $end
$var reg 1 # clk $end
$var reg 1 $ clrn $end
$var reg 1 % prn $end
$var reg 1 & t $end
$scope module tf1 $end
$var wire 1 # clk $end
$var wire 1 $ clrn $end
$var wire 1 " nq $end
$var wire 1 % prn $end
$var wire 1 ! q $end
$var wire 1 & t $end
$var wire 1 ' w1 $end
$var wire 1 ( w2 $end
$var wire 1 ) w3 $end
$var wire 1 * w4 $end
$var wire 1 + w5 $end
$var wire 1 , w6 $end
$upscope $end
$upscope $end
$enddefinitions $end
#0
$dumpvars
1,
0+
0*
1)
1(
1'
1&
0%
1$
1#
0"
1!
$end
#1
1+
0#
#2
0+
1#
#3
1+
0#
#4
0+
1#
#5
1+
0#
#6
0+
1#
#7
1+
0#
#8
0+
1#
#9
1+
0#
#10
0+
1#
#11
1+
0#
#12
0+
1#
#13
1+
0#
#14
0+
1#
#15
1+
0#
#16
0+
1#
#17
1+
0#
#18
0+
1#
#19
1+
0#
#20
0+
1#
#21
1+
0#
#22
0+
1#
#23
1+
0#
