saviour/UTEC/Arqui/lab/lab_03/ejercicio_1/JKFF/Behavioral/jkff.v
module jkff(prn, j, k, clk, clrn, q, nq);

	input 	prn, j, k, clk, clrn;
	output 	q, nq;
	wire 	w1, w2, w3, w4, w5, w6, w7, w8, w9, w10, w11, w12, w13, w14, w15, w16;

	//Master JK Latch
	
	assign w1 = ~(nq & j & ~clk & clrn);
        assign w2 = ~(q & k & ~clk & prn);

        assign w3 = ~(w1 & prn & w4);
        assign w4 = ~(w2 & clrn & w3);

	//Slave D Latch
	
	assign w5 = ~(w3 & clrn & clk);
	assign w6 = ~(w4 & clk & prn);

	//Output
	
	assign q = ~(w5 & prn & nq);
	assign nq = ~(w6 & clrn & q);

endmodule

saviour/UTEC/Arqui/lab/lab_03/ejercicio_1/JKFF/Behavioral/jkff_tb.v
`timescale 1ns/1ns
module jkff_tb;
        reg prn, j, k, clk, clrn;

        wire q, nq;

        jkff jkff_1 (prn, j, k, clk, clrn, q, nq); 

        initial begin
                prn = 0;
                j = 0;
		k = 0;
                clk = 1;
                clrn = 1;

                $display("time\tprn\tj\tk\tclk\tclrn\tq\tnq"); $monitor("%2d:\t%b\t%b\t%b\t%b\t%b\t%b\t%b",$time, prn, j, k, clk, clrn, q, nq);
                #23 $finish;
        end

	initial begin
        #3 j = 1;
        #5 j = 0;
        #7 j = 1;
        #15 j = 0;
        end

	initial begin
	#1 k = 1;
        #3 k = 0;
        #7 k = 1;
        #15 k = 0;	
	end

        always #1 clk = !clk;
	always #3 prn = !prn;
        initial begin
                $dumpfile("jkff.vcd");
                $dumpvars;
        end

        endmodule

saviour/UTEC/Arqui/lab/lab_03/ejercicio_1/JKFF/Behavioral/jkff.vcd
$date
	Mon May 18 23:21:10 2020
$end
$version
	Icarus Verilog
$end
$timescale
	1ns
$end
$scope module jkff_tb $end
$var wire 1 ! q $end
$var wire 1 " nq $end
$var reg 1 # clk $end
$var reg 1 $ clrn $end
$var reg 1 % j $end
$var reg 1 & k $end
$var reg 1 ' prn $end
$scope module jkff_1 $end
$var wire 1 # clk $end
$var wire 1 $ clrn $end
$var wire 1 % j $end
$var wire 1 & k $end
$var wire 1 " nq $end
$var wire 1 ' prn $end
$var wire 1 ! q $end
$var wire 1 ( w1 $end
$var wire 1 ) w2 $end
$var wire 1 * w3 $end
$var wire 1 + w4 $end
$var wire 1 , w5 $end
$var wire 1 - w6 $end
$upscope $end
$upscope $end
$enddefinitions $end
#0
$dumpvars
1-
0,
0+
1*
1)
1(
0'
0&
0%
1$
1#
0"
1!
$end
#1
1,
0#
1&
#2
0,
1#
#3
0*
1+
0)
1,
0#
1'
1%
#4
0!
1"
1)
0-
1#
0&
#5
0+
1*
0(
1-
0#
#6
0"
1(
1!
0,
1#
0'
#7
1,
0#
#8
0,
1#
0%
#9
1,
0#
1'
#10
0,
1#
#11
0*
1+
0)
1,
0#
1&
#12
0,
0+
1*
1)
1#
0'
#13
1,
0#
#14
0,
1#
#15
0*
1+
0)
1,
0#
1'
1%
#16
0!
1"
1)
0-
1#
#17
0+
1*
0(
1-
0#
#18
0"
1(
1!
0,
1#
0'
#19
1,
0#
#20
0,
1#
#21
0*
1+
0)
1,
0#
1'
#22
0!
1"
1)
0-
1#
#23
0+
1*
0(
1-
0#
