saviour/UTEC/Arqui/lab/lab_02/ejercicio_4/ejercicio_4.v
module ejercicio_4 (in_1, en, out_1);
	input [2:0] in_1;
	input en;
	output [7:0] out_1;

	assign out_1[0] = in_1 == 0? en : 0;
	assign out_1[1] = in_1 == 1? en : 0;
	assign out_1[2] = in_1 == 2? en : 0;
        assign out_1[3] = in_1 == 3? en : 0;
        assign out_1[4] = in_1 == 4? en : 0;
        assign out_1[5] = in_1 == 5? en : 0;
        assign out_1[6] = in_1 == 6? en : 0;
        assign out_1[7] = in_1 == 7? en : 0;
endmodule

saviour/UTEC/Arqui/lab/lab_02/ejercicio_4/ejercicio_4_tb.v
`timescale 1ns/1ns
module ejercicio_4_tb;
        reg [2:0] in_1;
        reg en;
        wire [7:0] out_1, out_2;
	
       ejercicio_4 e4 (in_1, en, out_1);
       
      initial begin	
                in_1 = 0;
                en = 1;

                $display("time\ten\tin_1\tout_1"); $monitor("%2d:\t%b\t%b\t%b",$time, 
en, in_1, out_1);
                #9 $finish;
        end

        always #1 in_1 = in_1 +1;
       	always #2 in_1 = in_1; 
        always #3 in_1 = in_1;
        always #4 in_1 = in_1;
        always #5 in_1 = in_1;
        always #6 in_1 = in_1;
        always #7 in_1 = in_1;
 
        always #8 en = ~en;


        initial begin
                $dumpfile("ejercicio_4.vcd");
                $dumpvars;
        end

endmodule

saviour/UTEC/Arqui/lab/lab_02/ejercicio_4/ejercicio_4.vcd
$date
	Tue May  5 08:13:42 2020
$end
$version
	Icarus Verilog
$end
$timescale
	1ns
$end
$scope module ejercicio_4_tb $end
$var wire 8 ! out_1 [7:0] $end
$var reg 1 " en $end
$var reg 3 # in_1 [2:0] $end
$scope module e4 $end
$var wire 1 " en $end
$var wire 3 $ in_1 [2:0] $end
$var wire 8 % out_1 [7:0] $end
$upscope $end
$upscope $end
$enddefinitions $end
#0
$dumpvars
b1 %
b0 $
b0 #
1"
b1 !
$end
#1
b10 !
b10 %
b1 #
b1 $
#2
b100 !
b100 %
b10 #
b10 $
#3
b1000 !
b1000 %
b11 #
b11 $
#4
b10000 !
b10000 %
b100 #
b100 $
#5
b100000 !
b100000 %
b101 #
b101 $
#6
b1000000 !
b1000000 %
b110 #
b110 $
#7
b10000000 !
b10000000 %
b111 #
b111 $
#8
b0 !
b0 %
b0 #
b0 $
0"
#9
b1 #
b1 $
