saviour/UTEC/Arqui/lab/lab_04/slides/sl3/snail.v
module snail(clk, rst, bit, y);
	input clk, rst, bit;
	output y;

	reg[3:0] state_1, state_2;

	parameter s0 = 4'b0000;
	parameter s1 = 4'b0001;
	parameter s2 = 4'b0010;
	parameter s3 = 4'b0100;
	parameter s4 = 4'b1000;

	always @ (posedge clk, posedge rst)
		if(rst) state_1 = s0;
		else state_1 <= state_2;

	always @(*)
	case(state_1)
		s0: if(bit)state_2 = s1;
			else state_2 = s0;

		s1: if(bit)state_2 = s2;
                        else state_2 = s0;

		s2: if(bit)state_2 = s3;
                        else state_2 = s2;

		s3: if(bit)state_2 = s4;
                        else state_2 = s0;

		s4: if(bit)state_2 = s2;
                        else state_2 = s0;
	endcase
assign y = (state_1 == s4);
endmodule

saviour/UTEC/Arqui/lab/lab_04/slides/sl3/snail_tb.v
`timescale 1ns/1ns
module snail_tb;
	reg clk, rst, bit;
	output y;

	always #1 clk = ~clk;
	always #1 rst = 0;
	always #7 bit = ~bit;

	snail sna(clk, rst, bit, y);
	initial begin
		rst = 1;
		clk = 1;
		bit = 0;
		bit = 1;
		#2 bit = 0;
		bit = 1;
		#3 bit = 0;
		#7 $finish;
	end

	initial begin
		 $dumpfile("nail.vcd");
		 $dumpvars;
	 end
	 endmodule

saviour/UTEC/Arqui/lab/lab_04/slides/sl3/nail.vcd
$date
	Sun May 31 20:32:31 2020
$end
$version
	Icarus Verilog
$end
$timescale
	1ns
$end
$scope module snail_tb $end
$var wire 1 ! y $end
$var reg 1 " bit $end
$var reg 1 # clk $end
$var reg 1 $ rst $end
$scope module sna $end
$var wire 1 " bit $end
$var wire 1 # clk $end
$var wire 1 $ rst $end
$var wire 1 ! y $end
$var reg 4 % state_1 [3:0] $end
$var reg 4 & state_2 [3:0] $end
$upscope $end
$upscope $end
$enddefinitions $end
#0
$dumpvars
b1 &
b0 %
1$
1#
1"
0!
$end
#1
0$
0#
#2
b10 &
b1 %
1#
1"
#3
0#
#4
b100 &
b10 %
1#
#5
b10 &
0#
0"
#6
1#
#7
b100 &
0#
1"
#8
b1000 &
b100 %
1#
#9
0#
#10
b10 &
1!
b1000 %
1#
#11
0#
#12
b100 &
0!
b10 %
1#
