saviour/UTEC/Arqui/lab/lab_04/slides/sl1/a_gt_eq_six.v
module a_gt_eq_six(a2,a1,a0,a_gt_eq_six);
	input a2, a1, a0;
	output a_gt_eq_six;
	reg a_gt_eq_six; //variables are reg in always

	always @ (a2 or a1 or a0)
	begin
		if(a2 & a1)
			a_gt_eq_six = 1'b1;
		else
			a_gt_eq_six = 1'b0;
	end
	endmodule

saviour/UTEC/Arqui/lab/lab_04/slides/sl1/a_gt_eq_six_tb.v
module a_gt_eq_six_tb;
reg a2,a1, a0;

initial
begin: estimulate_design
	reg [3:0] invect;
	for(invect = 0; invect < 8; invect = invect + 1)
	begin
		{a2, a1, a0} = invect [3:0];
		#10 $display("a2. a1. a0 = %b, a_gt_eq_six = %b", {a2, a1, a0}, a_gt_eq_six);
	end
end

a_gt_eq_six inst1 (a2, a1, a0, a_gt_eq_six);

        initial begin
                $dumpfile("a_gt_eq_six.vcd");
                $dumpvars;
        end
endmodule

saviour/UTEC/Arqui/lab/lab_04/slides/sl1/a_gt_eq_six.vcd
$date
	Sun May 31 18:43:36 2020
$end
$version
	Icarus Verilog
$end
$timescale
	1s
$end
$scope module a_gt_eq_six_tb $end
$var wire 1 ! a_gt_eq_six $end
$var reg 1 " a0 $end
$var reg 1 # a1 $end
$var reg 1 $ a2 $end
$scope module inst1 $end
$var wire 1 " a0 $end
$var wire 1 # a1 $end
$var wire 1 $ a2 $end
$var reg 1 ! a_gt_eq_six $end
$upscope $end
$scope begin estimulate_design $end
$var reg 4 % invect [3:0] $end
$upscope $end
$upscope $end
$enddefinitions $end
#0
$dumpvars
b0 %
0$
0#
0"
0!
$end
#10
1"
b1 %
#20
1#
0"
b10 %
#30
1"
b11 %
#40
1$
0#
0"
b100 %
#50
1"
b101 %
#60
1!
1#
0"
b110 %
#70
1"
b111 %
#80
b1000 %
