saviour/UTEC/Arqui/lab/lab_03/ejercicio_1/TFF/Structural/tff.v
module tff(prn, t, clk, clrn, q, nq);

        input   prn, t, clk, clrn;
        output  q, nq;
        wire    w1, w2, w3, w4, w5, w6, w7, w8, w9, w10, w11, w12, w13, w14, w15, w16;

        //Master JK Latch
		
	or a1(w1, ~nq, ~t);
	or a2(w2, clk, ~clrn);
	or a3(w3, w1, w2);

	//w3

	or a4(w4, ~q, ~t);
        or a5(w5, clk, ~prn);
        or a6(w6, w4, w5);

	//w6

        or a7(w7, ~w3, ~prn);
        or a8(w8, w7, ~w10);

	//w3->w8
	
        or a9(w9, ~clrn, ~w6);
        or a10(w10, w9, ~w8);

	//w6->w10


	//Slave D Latch

        or a11(w11, ~w8, ~clrn);
        or a12(w12, w11, ~clk);


	//w8->w12

	or a13(w13, ~w10, ~prn);
        or a14(w14, w13, ~clk);

	//w10->w14

        //Output
	
	or a15(w15, ~w12, ~prn);
        or a16(q, w15, ~nq);

        or a17(w16, ~w14, ~clrn);
        or a18(nq, w16, ~q);



endmodule

saviour/UTEC/Arqui/lab/lab_03/ejercicio_1/TFF/Structural/tff_tb.v
`timescale 1ns/1ns
module tff_tb;
        reg prn, t, clk, clrn;

        wire q, nq;

        tff tf1 (prn, t, clk, clrn, q, nq);
        initial begin
        	prn = 0;
                t = 1;
		clk = 1;
		clrn = 1;

                $display("time\tprn\tt\tclk\tclrn\tq\tnq"); $monitor("%2d:\t%b\t%b\t%b\t%b\t%b\t%b",$time, prn, t, clk, clrn, q, nq);
                #23 $finish;
        end

        always #1 clk = !clk;
	always #3 prn = !prn;
        initial begin
                $dumpfile("tff.vcd");
                $dumpvars;
        end

        endmodule

saviour/UTEC/Arqui/lab/lab_03/ejercicio_1/TFF/Structural/tff.vcd
$date
	Mon May 18 23:48:08 2020
$end
$version
	Icarus Verilog
$end
$timescale
	1ns
$end
$scope module tff_tb $end
$var wire 1 ! q $end
$var wire 1 " nq $end
$var reg 1 # clk $end
$var reg 1 $ clrn $end
$var reg 1 % prn $end
$var reg 1 & t $end
$scope module tf1 $end
$var wire 1 # clk $end
$var wire 1 $ clrn $end
$var wire 1 " nq $end
$var wire 1 % prn $end
$var wire 1 ! q $end
$var wire 1 & t $end
$var wire 1 ' w1 $end
$var wire 1 ( w10 $end
$var wire 1 ) w11 $end
$var wire 1 * w12 $end
$var wire 1 + w13 $end
$var wire 1 , w14 $end
$var wire 1 - w15 $end
$var wire 1 . w16 $end
$var wire 1 / w2 $end
$var wire 1 0 w3 $end
$var wire 1 1 w4 $end
$var wire 1 2 w5 $end
$var wire 1 3 w6 $end
$var wire 1 4 w7 $end
$var wire 1 5 w8 $end
$var wire 1 6 w9 $end
$upscope $end
$upscope $end
$enddefinitions $end
#0
$dumpvars
06
15
14
13
12
01
10
1/
0.
1-
1,
1+
0*
0)
0(
1'
1&
0%
1$
1#
0"
1!
$end
#1
1*
0/
0#
#2
0*
1/
1#
#3
1)
0+
05
1(
16
0-
03
1*
04
0/
02
0#
1%
#4
11
0!
0'
1"
06
1.
13
0,
1/
12
1#
#5
1+
0(
0)
15
14
0.
00
1,
0/
02
0#
#6
1'
0"
01
1!
10
0*
1-
1/
12
1#
0%
#7
1*
0/
0#
#8
0*
1/
1#
#9
1)
0+
05
1(
16
0-
03
1*
04
0/
02
0#
1%
#10
11
0!
0'
1"
06
1.
13
0,
1/
12
1#
#11
1+
0(
0)
15
14
0.
00
1,
0/
02
0#
#12
1'
0"
01
1!
10
0*
1-
1/
12
1#
0%
#13
1*
0/
0#
#14
0*
1/
1#
#15
1)
0+
05
1(
16
0-
03
1*
04
0/
02
0#
1%
#16
11
0!
0'
1"
06
1.
13
0,
1/
12
1#
#17
1+
0(
0)
15
14
0.
00
1,
0/
02
0#
#18
1'
0"
01
1!
10
0*
1-
1/
12
1#
0%
#19
1*
0/
0#
#20
0*
1/
1#
#21
1)
0+
05
1(
16
0-
03
1*
04
0/
02
0#
1%
#22
11
0!
0'
1"
06
1.
13
0,
1/
12
1#
#23
1+
0(
0)
15
14
0.
00
1,
0/
02
0#
