saviour/UTEC/Arqui/lab/lab_02/ejercicio_3/c/ejercicio_3_a.v
module ejercicio_3_a(in_1,sel_1, out_1, out_2);
	input [15:0] in_1; 
	input sel_1;
	output [15:0] out_1, out_2;

	assign out_1 = (in_1 && ~sel_1)?in_1:0;

	assign out_2 = (in_1 && sel_1)? in_1:0;

endmodule

saviour/UTEC/Arqui/lab/lab_02/ejercicio_3/c/ejercicio_3_b.v
module ejercicio_3_b(in_1, sel_1, sel_2, sel_3, out_1, out_2, out_3, out_4, out_5, out_6, out_7, out_8);
	input [15:0] in_1;
	input sel_1, sel_2, sel_3;
	output [15:0] out_1, out_2, out_3, out_4, out_5, out_6, out_7, out_8;
	wire [15:0] wi_1, wi_2, wi_3, wi_4, wi_5, wi_6;

	ejercicio_3_a a1(in_1, sel_3, wi_1, wi_2);

	ejercicio_3_a a2_0(wi_1, sel_2, wi_3, wi_4);
	ejercicio_3_a a2_1(wi_2, sel_2, wi_5, wi_6);

	ejercicio_3_a a3_0(wi_3, sel_1, out_1, out_2);
        ejercicio_3_a a3_1(wi_4, sel_1, out_3, out_4);
        ejercicio_3_a a3_2(wi_5, sel_1, out_5, out_6);
	ejercicio_3_a a3_3(wi_6, sel_1, out_7, out_8);



endmodule

saviour/UTEC/Arqui/lab/lab_02/ejercicio_3/b/ejercicio_3_b_tb.v
`timescale 1ns/1ns
module ejercicio_3_b_tb;
        reg [15:0] in_1;
        reg sel_1, sel_2, sel_3;

        wire [15:0] out_1, out_2, out_3, out_4, out_5, out_6, out_7, out_8;

       ejercicio_3_b e3_a(in_1, sel_1, sel_2, sel_3, out_1, out_2, out_3, out_4, out_5, out_6, out_7, out_8);
        initial begin
                in_1 <= 1;
                sel_1 = 0;
		sel_2 = 0;
		sel_3 = 0;

                $display("time\tsel_1\tsel_2\tsel_3\tout_1\tout_2\tout_3\tout_4\tout_5\tout_6\tout_7\tout_8"); $monitor("%2d:\t%b\t%b\t%b\t%b\t%b\t%b\t%b\t%b\t%b\t%b\t%b",$time, sel_1, sel_2, sel_3, out_1, out_2, out_3, out_4, out_5, out_6, out_7, out_8);
                #7 $finish;
        end

        always #1 sel_1 = sel_1;
        always #1 sel_2 = sel_2;
        always #1 sel_3 = ~sel_3;

        always #2 sel_1 = sel_1;
        always #2 sel_2 = ~sel_2;
        always #2 sel_3 = sel_3;

        always #3 sel_1 = sel_1;
        always #3 sel_2 = sel_2;
        always #3 sel_3 = sel_3;

        always #4 sel_1 = ~sel_1;
        always #4 sel_2 = sel_2;
        always #4 sel_3 = sel_3;

        always #5 sel_1 = sel_1;
        always #5 sel_2 = sel_2;
        always #5 sel_3 = sel_3;

        always #6 sel_1 = sel_1;
        always #6 sel_2 = sel_2;
        always #6 sel_3 = sel_3;

        always #7 sel_1 = sel_1;
        always #7 sel_2 = sel_2;
        always #7 sel_3 = sel_3;


        initial begin
                $dumpfile("ejercicio_3_b.vcd");
                $dumpvars;
        end

endmodule

saviour/UTEC/Arqui/lab/lab_02/ejercicio_3/b/ejercicio_3_b.vcd
$date
	Tue May  5 08:08:33 2020
$end
$version
	Icarus Verilog
$end
$timescale
	1ns
$end
$scope module ejercicio_3_b_tb $end
$var wire 16 ! out_8 [15:0] $end
$var wire 16 " out_7 [15:0] $end
$var wire 16 # out_6 [15:0] $end
$var wire 16 $ out_5 [15:0] $end
$var wire 16 % out_4 [15:0] $end
$var wire 16 & out_3 [15:0] $end
$var wire 16 ' out_2 [15:0] $end
$var wire 16 ( out_1 [15:0] $end
$var reg 16 ) in_1 [15:0] $end
$var reg 1 * sel_1 $end
$var reg 1 + sel_2 $end
$var reg 1 , sel_3 $end
$scope module e3_a $end
$var wire 16 - in_1 [15:0] $end
$var wire 1 * sel_1 $end
$var wire 1 + sel_2 $end
$var wire 1 , sel_3 $end
$var wire 16 . wi_6 [15:0] $end
$var wire 16 / wi_5 [15:0] $end
$var wire 16 0 wi_4 [15:0] $end
$var wire 16 1 wi_3 [15:0] $end
$var wire 16 2 wi_2 [15:0] $end
$var wire 16 3 wi_1 [15:0] $end
$var wire 16 4 out_8 [15:0] $end
$var wire 16 5 out_7 [15:0] $end
$var wire 16 6 out_6 [15:0] $end
$var wire 16 7 out_5 [15:0] $end
$var wire 16 8 out_4 [15:0] $end
$var wire 16 9 out_3 [15:0] $end
$var wire 16 : out_2 [15:0] $end
$var wire 16 ; out_1 [15:0] $end
$scope module a1 $end
$var wire 16 < in_1 [15:0] $end
$var wire 1 , sel_1 $end
$var wire 16 = out_2 [15:0] $end
$var wire 16 > out_1 [15:0] $end
$upscope $end
$scope module a2_0 $end
$var wire 16 ? in_1 [15:0] $end
$var wire 1 + sel_1 $end
$var wire 16 @ out_2 [15:0] $end
$var wire 16 A out_1 [15:0] $end
$upscope $end
$scope module a2_1 $end
$var wire 16 B in_1 [15:0] $end
$var wire 1 + sel_1 $end
$var wire 16 C out_2 [15:0] $end
$var wire 16 D out_1 [15:0] $end
$upscope $end
$scope module a3_0 $end
$var wire 16 E in_1 [15:0] $end
$var wire 1 * sel_1 $end
$var wire 16 F out_2 [15:0] $end
$var wire 16 G out_1 [15:0] $end
$upscope $end
$scope module a3_1 $end
$var wire 16 H in_1 [15:0] $end
$var wire 1 * sel_1 $end
$var wire 16 I out_2 [15:0] $end
$var wire 16 J out_1 [15:0] $end
$upscope $end
$scope module a3_2 $end
$var wire 16 K in_1 [15:0] $end
$var wire 1 * sel_1 $end
$var wire 16 L out_2 [15:0] $end
$var wire 16 M out_1 [15:0] $end
$upscope $end
$scope module a3_3 $end
$var wire 16 N in_1 [15:0] $end
$var wire 1 * sel_1 $end
$var wire 16 O out_2 [15:0] $end
$var wire 16 P out_1 [15:0] $end
$upscope $end
$upscope $end
$upscope $end
$enddefinitions $end
#0
$dumpvars
b0 P
b0 O
b0 N
b0 M
b0 L
b0 K
b0 J
b0 I
b0 H
b1 G
b0 F
b1 E
b0 D
b0 C
b0 B
b1 A
b0 @
b1 ?
b1 >
b0 =
b1 <
b1 ;
b0 :
b0 9
b0 8
b0 7
b0 6
b0 5
b0 4
b1 3
b0 2
b1 1
b0 0
b0 /
b0 .
b1 -
0,
0+
0*
b1 )
b1 (
b0 '
b0 &
b0 %
b0 $
b0 #
b0 "
b0 !
$end
#1
b0 (
b0 ;
b0 G
b0 1
b0 A
b0 E
b1 $
b1 7
b1 M
b0 3
b0 >
b0 ?
b1 /
b1 D
b1 K
b1 2
b1 =
b1 B
1,
#2
b1 &
b1 9
b1 J
b1 0
b1 @
b1 H
b0 $
b0 7
b0 M
b1 3
b1 >
b1 ?
b0 /
b0 D
b0 K
b0 "
b0 5
b0 P
b0 2
b0 =
b0 B
b0 .
b0 C
b0 N
0,
1+
#3
b0 &
b0 9
b0 J
b0 0
b0 @
b0 H
b1 "
b1 5
b1 P
b0 3
b0 >
b0 ?
b1 .
b1 C
b1 N
b1 2
b1 =
b1 B
1,
#4
b1 '
b1 :
b1 F
b1 1
b1 A
b1 E
b1 3
b1 >
b1 ?
b0 "
b0 5
b0 P
b0 2
b0 =
b0 B
b0 .
b0 C
b0 N
b0 !
b0 4
b0 O
0,
0+
1*
#5
b0 '
b0 :
b0 F
b0 1
b0 A
b0 E
b1 #
b1 6
b1 L
b0 3
b0 >
b0 ?
b1 /
b1 D
b1 K
b1 2
b1 =
b1 B
1,
#6
b1 %
b1 8
b1 I
b1 0
b1 @
b1 H
b0 #
b0 6
b0 L
b1 3
b1 >
b1 ?
b0 /
b0 D
b0 K
b0 !
b0 4
b0 O
b0 2
b0 =
b0 B
b0 .
b0 C
b0 N
0,
1+
#7
b0 %
b0 8
b0 I
b0 0
b0 @
b0 H
b1 !
b1 4
b1 O
b0 3
b0 >
b0 ?
b1 .
b1 C
b1 N
b1 2
b1 =
b1 B
1,
