saviour/UTEC/Arqui/lab/lab_03/ejercicio_1/JKFF/Structural/jkff.v
module jkff(prn, j, k, clk, clrn, q, nq);

        input   prn, j, k, clk, clrn;
        output  q, nq;
        wire    w1, w2, w3, w4, w5, w6;

        //Master JK Latch
		
	or a1(w1, ~nq, ~j);
	or a2(w2, clk, ~clrn);
	or a3(w3, w1, w2);

	//w3

	or a4(w4, ~q, ~k);
        or a5(w5, clk, ~prn);
        or a6(w6, w4, w5);

	//w6

        or a7(w7, ~w3, ~prn);
        or a8(w8, w7, ~w10);

	//w3->w8
	
        or a9(w9, ~clrn, ~w6);
        or a10(w10, w9, ~w8);

	//w6->w10


	//Slave D Latch

        or a11(w11, ~w8, ~clrn);
        or a12(w12, w11, ~clk);


	//w8->w12

	or a13(w13, ~w10, ~prn);
        or a14(w14, w13, ~clk);

	//w10->w14

        //Output
	
	or a15(w15, ~w12, ~prn);
        or a16(q, w15, ~nq);

        or a17(w16, ~w14, ~clrn);
        or a18(nq, w16, ~q);



endmodule

saviour/UTEC/Arqui/lab/lab_03/ejercicio_1/JKFF/Behavioral/jkff_tb.v
`timescale 1ns/1ns
module jkff_tb;
        reg prn, j, k, clk, clrn;

        wire q, nq;

        jkff jkff_1 (prn, j, k, clk, clrn, q, nq); 

        initial begin
                prn = 0;
                j = 0;
		k = 0;
                clk = 1;
                clrn = 1;

                $display("time\tprn\tj\tk\tclk\tclrn\tq\tnq"); $monitor("%2d:\t%b\t%b\t%b\t%b\t%b\t%b\t%b",$time, prn, j, k, clk, clrn, q, nq);
                #23 $finish;
        end

	initial begin
        #3 j = 1;
        #5 j = 0;
        #7 j = 1;
        #15 j = 0;
        end

	initial begin
	#1 k = 1;
        #3 k = 0;
        #7 k = 1;
        #15 k = 0;	
	end

        always #1 clk = !clk;
	always #3 prn = !prn;
        initial begin
                $dumpfile("jkff.vcd");
                $dumpvars;
        end

        endmodule

saviour/UTEC/Arqui/lab/lab_03/ejercicio_1/JKFF/Structural/jkff.vcd
$date
	Mon May 18 23:33:15 2020
$end
$version
	Icarus Verilog
$end
$timescale
	1ns
$end
$scope module jkff_tb $end
$var wire 1 ! q $end
$var wire 1 " nq $end
$var reg 1 # clk $end
$var reg 1 $ clrn $end
$var reg 1 % j $end
$var reg 1 & k $end
$var reg 1 ' prn $end
$scope module jkff_1 $end
$var wire 1 # clk $end
$var wire 1 $ clrn $end
$var wire 1 % j $end
$var wire 1 & k $end
$var wire 1 " nq $end
$var wire 1 ' prn $end
$var wire 1 ! q $end
$var wire 1 ( w1 $end
$var wire 1 ) w10 $end
$var wire 1 * w11 $end
$var wire 1 + w12 $end
$var wire 1 , w13 $end
$var wire 1 - w14 $end
$var wire 1 . w15 $end
$var wire 1 / w16 $end
$var wire 1 0 w2 $end
$var wire 1 1 w3 $end
$var wire 1 2 w4 $end
$var wire 1 3 w5 $end
$var wire 1 4 w6 $end
$var wire 1 5 w7 $end
$var wire 1 6 w8 $end
$var wire 1 7 w9 $end
$upscope $end
$upscope $end
$enddefinitions $end
#0
$dumpvars
07
16
15
14
13
12
11
10
0/
1.
1-
1,
0+
0*
0)
1(
0'
0&
0%
1$
1#
0"
1!
$end
#1
1+
02
00
0#
1&
#2
0+
10
1#
#3
1*
0,
06
1)
17
0.
04
1+
05
00
03
0#
1'
1%
#4
0!
0(
1"
07
1/
14
0-
12
10
13
1#
0&
#5
1,
0)
0*
16
15
0/
01
1-
00
03
0#
#6
1(
0"
1!
11
0+
1.
10
13
1#
0'
#7
1+
00
0#
#8
0+
10
1#
0%
#9
0.
1+
05
00
03
0#
1'
#10
1.
0+
10
13
1#
#11
1*
0,
06
1)
17
0.
04
1+
02
00
03
0#
1&
#12
0+
0)
0*
07
16
14
15
1,
1.
10
13
1#
0'
#13
1+
00
0#
#14
0+
10
1#
#15
1*
0,
06
1)
17
0.
04
1+
05
00
03
0#
1'
1%
#16
12
0!
0(
1"
07
1/
14
0-
10
13
1#
#17
1,
0)
0*
16
15
0/
01
1-
00
03
0#
#18
1(
0"
02
1!
11
0+
1.
10
13
1#
0'
#19
1+
00
0#
#20
0+
10
1#
#21
1*
0,
06
1)
17
0.
04
1+
05
00
03
0#
1'
#22
12
0!
0(
1"
07
1/
14
0-
10
13
1#
#23
1,
0)
0*
16
15
0/
01
1-
00
03
0#
