saviour/UTEC/Arqui/lab/lab_02/ejercicio_5/ejercicio_5.v
module ejercicio_5(in_1, en, out_1, g);
	input wire[7:0] in_1;
	input en;
	output reg[2:0] out_1;
	output g;

	always @*
	begin
		if(!en)
			out_1 = 8'o0;
		else 
			casex(in_1)
		
	        		8'b00000001 : out_1 = 8'o0;
                		8'b0000001x : out_1 = 8'o1;
                		8'b000001xx : out_1 = 8'o2;
                		8'b00001xxx : out_1 = 8'o3;
                		8'b0001xxxx : out_1 = 8'o4;
                		8'b001xxxxx : out_1 = 8'o5;
                		8'b01xxxxxx : out_1 = 8'o6;
                		8'b1xxxxxxx : out_1 = 8'o7;

				default: begin
					out_1 = 8'o0;
				end
			endcase
	end
	assign g = (en && in_1)? 1:0;

endmodule

saviour/UTEC/Arqui/lab/lab_02/ejercicio_5/ejercicio_5_tb.v
`timescale 1ns/1ns
module ejercicio_5_tb;
        reg [7:0] in_1;
        reg en;
        wire [2:0] out_1;
	wire g;

       ejercicio_5 e5 (in_1, en, out_1, g);

      initial begin
                in_1 = 0;
                en = 1;

                $display("time\ten\tin_1\tout_1"); $monitor("%2d:\t%b\t%b\t%b\t%b",$time,
en, in_1, out_1, g);
                #257 $finish;
        end

        always #1 in_1 = in_1 +1;
        

        always #257 en = ~en;


        initial begin
                $dumpfile("ejercicio_5.vcd");
                $dumpvars;
        end

endmodule

saviour/UTEC/Arqui/lab/lab_02/ejercicio_5/ejercicio_5.vcd
$date
	Tue May  5 08:15:45 2020
$end
$version
	Icarus Verilog
$end
$timescale
	1ns
$end
$scope module ejercicio_5_tb $end
$var wire 3 ! out_1 [2:0] $end
$var wire 1 " g $end
$var reg 1 # en $end
$var reg 8 $ in_1 [7:0] $end
$scope module e5 $end
$var wire 1 # en $end
$var wire 8 % in_1 [7:0] $end
$var wire 1 " g $end
$var reg 3 & out_1 [2:0] $end
$upscope $end
$upscope $end
$enddefinitions $end
#0
$dumpvars
b0 &
b0 %
b0 $
1#
0"
b0 !
$end
#1
1"
b1 $
b1 %
#2
b1 !
b1 &
b10 $
b10 %
#3
b11 $
b11 %
#4
b10 !
b10 &
b100 $
b100 %
#5
b101 $
b101 %
#6
b110 $
b110 %
#7
b111 $
b111 %
#8
b11 !
b11 &
b1000 $
b1000 %
#9
b1001 $
b1001 %
#10
b1010 $
b1010 %
#11
b1011 $
b1011 %
#12
b1100 $
b1100 %
#13
b1101 $
b1101 %
#14
b1110 $
b1110 %
#15
b1111 $
b1111 %
#16
b100 !
b100 &
b10000 $
b10000 %
#17
b10001 $
b10001 %
#18
b10010 $
b10010 %
#19
b10011 $
b10011 %
#20
b10100 $
b10100 %
#21
b10101 $
b10101 %
#22
b10110 $
b10110 %
#23
b10111 $
b10111 %
#24
b11000 $
b11000 %
#25
b11001 $
b11001 %
#26
b11010 $
b11010 %
#27
b11011 $
b11011 %
#28
b11100 $
b11100 %
#29
b11101 $
b11101 %
#30
b11110 $
b11110 %
#31
b11111 $
b11111 %
#32
b101 !
b101 &
b100000 $
b100000 %
#33
b100001 $
b100001 %
#34
b100010 $
b100010 %
#35
b100011 $
b100011 %
#36
b100100 $
b100100 %
#37
b100101 $
b100101 %
#38
b100110 $
b100110 %
#39
b100111 $
b100111 %
#40
b101000 $
b101000 %
#41
b101001 $
b101001 %
#42
b101010 $
b101010 %
#43
b101011 $
b101011 %
#44
b101100 $
b101100 %
#45
b101101 $
b101101 %
#46
b101110 $
b101110 %
#47
b101111 $
b101111 %
#48
b110000 $
b110000 %
#49
b110001 $
b110001 %
#50
b110010 $
b110010 %
#51
b110011 $
b110011 %
#52
b110100 $
b110100 %
#53
b110101 $
b110101 %
#54
b110110 $
b110110 %
#55
b110111 $
b110111 %
#56
b111000 $
b111000 %
#57
b111001 $
b111001 %
#58
b111010 $
b111010 %
#59
b111011 $
b111011 %
#60
b111100 $
b111100 %
#61
b111101 $
b111101 %
#62
b111110 $
b111110 %
#63
b111111 $
b111111 %
#64
b110 !
b110 &
b1000000 $
b1000000 %
#65
b1000001 $
b1000001 %
#66
b1000010 $
b1000010 %
#67
b1000011 $
b1000011 %
#68
b1000100 $
b1000100 %
#69
b1000101 $
b1000101 %
#70
b1000110 $
b1000110 %
#71
b1000111 $
b1000111 %
#72
b1001000 $
b1001000 %
#73
b1001001 $
b1001001 %
#74
b1001010 $
b1001010 %
#75
b1001011 $
b1001011 %
#76
b1001100 $
b1001100 %
#77
b1001101 $
b1001101 %
#78
b1001110 $
b1001110 %
#79
b1001111 $
b1001111 %
#80
b1010000 $
b1010000 %
#81
b1010001 $
b1010001 %
#82
b1010010 $
b1010010 %
#83
b1010011 $
b1010011 %
#84
b1010100 $
b1010100 %
#85
b1010101 $
b1010101 %
#86
b1010110 $
b1010110 %
#87
b1010111 $
b1010111 %
#88
b1011000 $
b1011000 %
#89
b1011001 $
b1011001 %
#90
b1011010 $
b1011010 %
#91
b1011011 $
b1011011 %
#92
b1011100 $
b1011100 %
#93
b1011101 $
b1011101 %
#94
b1011110 $
b1011110 %
#95
b1011111 $
b1011111 %
#96
b1100000 $
b1100000 %
#97
b1100001 $
b1100001 %
#98
b1100010 $
b1100010 %
#99
b1100011 $
b1100011 %
#100
b1100100 $
b1100100 %
#101
b1100101 $
b1100101 %
#102
b1100110 $
b1100110 %
#103
b1100111 $
b1100111 %
#104
b1101000 $
b1101000 %
#105
b1101001 $
b1101001 %
#106
b1101010 $
b1101010 %
#107
b1101011 $
b1101011 %
#108
b1101100 $
b1101100 %
#109
b1101101 $
b1101101 %
#110
b1101110 $
b1101110 %
#111
b1101111 $
b1101111 %
#112
b1110000 $
b1110000 %
#113
b1110001 $
b1110001 %
#114
b1110010 $
b1110010 %
#115
b1110011 $
b1110011 %
#116
b1110100 $
b1110100 %
#117
b1110101 $
b1110101 %
#118
b1110110 $
b1110110 %
#119
b1110111 $
b1110111 %
#120
b1111000 $
b1111000 %
#121
b1111001 $
b1111001 %
#122
b1111010 $
b1111010 %
#123
b1111011 $
b1111011 %
#124
b1111100 $
b1111100 %
#125
b1111101 $
b1111101 %
#126
b1111110 $
b1111110 %
#127
b1111111 $
b1111111 %
#128
b111 !
b111 &
b10000000 $
b10000000 %
#129
b10000001 $
b10000001 %
#130
b10000010 $
b10000010 %
#131
b10000011 $
b10000011 %
#132
b10000100 $
b10000100 %
#133
b10000101 $
b10000101 %
#134
b10000110 $
b10000110 %
#135
b10000111 $
b10000111 %
#136
b10001000 $
b10001000 %
#137
b10001001 $
b10001001 %
#138
b10001010 $
b10001010 %
#139
b10001011 $
b10001011 %
#140
b10001100 $
b10001100 %
#141
b10001101 $
b10001101 %
#142
b10001110 $
b10001110 %
#143
b10001111 $
b10001111 %
#144
b10010000 $
b10010000 %
#145
b10010001 $
b10010001 %
#146
b10010010 $
b10010010 %
#147
b10010011 $
b10010011 %
#148
b10010100 $
b10010100 %
#149
b10010101 $
b10010101 %
#150
b10010110 $
b10010110 %
#151
b10010111 $
b10010111 %
#152
b10011000 $
b10011000 %
#153
b10011001 $
b10011001 %
#154
b10011010 $
b10011010 %
#155
b10011011 $
b10011011 %
#156
b10011100 $
b10011100 %
#157
b10011101 $
b10011101 %
#158
b10011110 $
b10011110 %
#159
b10011111 $
b10011111 %
#160
b10100000 $
b10100000 %
#161
b10100001 $
b10100001 %
#162
b10100010 $
b10100010 %
#163
b10100011 $
b10100011 %
#164
b10100100 $
b10100100 %
#165
b10100101 $
b10100101 %
#166
b10100110 $
b10100110 %
#167
b10100111 $
b10100111 %
#168
b10101000 $
b10101000 %
#169
b10101001 $
b10101001 %
#170
b10101010 $
b10101010 %
#171
b10101011 $
b10101011 %
#172
b10101100 $
b10101100 %
#173
b10101101 $
b10101101 %
#174
b10101110 $
b10101110 %
#175
b10101111 $
b10101111 %
#176
b10110000 $
b10110000 %
#177
b10110001 $
b10110001 %
#178
b10110010 $
b10110010 %
#179
b10110011 $
b10110011 %
#180
b10110100 $
b10110100 %
#181
b10110101 $
b10110101 %
#182
b10110110 $
b10110110 %
#183
b10110111 $
b10110111 %
#184
b10111000 $
b10111000 %
#185
b10111001 $
b10111001 %
#186
b10111010 $
b10111010 %
#187
b10111011 $
b10111011 %
#188
b10111100 $
b10111100 %
#189
b10111101 $
b10111101 %
#190
b10111110 $
b10111110 %
#191
b10111111 $
b10111111 %
#192
b11000000 $
b11000000 %
#193
b11000001 $
b11000001 %
#194
b11000010 $
b11000010 %
#195
b11000011 $
b11000011 %
#196
b11000100 $
b11000100 %
#197
b11000101 $
b11000101 %
#198
b11000110 $
b11000110 %
#199
b11000111 $
b11000111 %
#200
b11001000 $
b11001000 %
#201
b11001001 $
b11001001 %
#202
b11001010 $
b11001010 %
#203
b11001011 $
b11001011 %
#204
b11001100 $
b11001100 %
#205
b11001101 $
b11001101 %
#206
b11001110 $
b11001110 %
#207
b11001111 $
b11001111 %
#208
b11010000 $
b11010000 %
#209
b11010001 $
b11010001 %
#210
b11010010 $
b11010010 %
#211
b11010011 $
b11010011 %
#212
b11010100 $
b11010100 %
#213
b11010101 $
b11010101 %
#214
b11010110 $
b11010110 %
#215
b11010111 $
b11010111 %
#216
b11011000 $
b11011000 %
#217
b11011001 $
b11011001 %
#218
b11011010 $
b11011010 %
#219
b11011011 $
b11011011 %
#220
b11011100 $
b11011100 %
#221
b11011101 $
b11011101 %
#222
b11011110 $
b11011110 %
#223
b11011111 $
b11011111 %
#224
b11100000 $
b11100000 %
#225
b11100001 $
b11100001 %
#226
b11100010 $
b11100010 %
#227
b11100011 $
b11100011 %
#228
b11100100 $
b11100100 %
#229
b11100101 $
b11100101 %
#230
b11100110 $
b11100110 %
#231
b11100111 $
b11100111 %
#232
b11101000 $
b11101000 %
#233
b11101001 $
b11101001 %
#234
b11101010 $
b11101010 %
#235
b11101011 $
b11101011 %
#236
b11101100 $
b11101100 %
#237
b11101101 $
b11101101 %
#238
b11101110 $
b11101110 %
#239
b11101111 $
b11101111 %
#240
b11110000 $
b11110000 %
#241
b11110001 $
b11110001 %
#242
b11110010 $
b11110010 %
#243
b11110011 $
b11110011 %
#244
b11110100 $
b11110100 %
#245
b11110101 $
b11110101 %
#246
b11110110 $
b11110110 %
#247
b11110111 $
b11110111 %
#248
b11111000 $
b11111000 %
#249
b11111001 $
b11111001 %
#250
b11111010 $
b11111010 %
#251
b11111011 $
b11111011 %
#252
b11111100 $
b11111100 %
#253
b11111101 $
b11111101 %
#254
b11111110 $
b11111110 %
#255
b11111111 $
b11111111 %
#256
0"
b0 !
b0 &
b0 $
b0 %
#257
b1 $
b1 %
0#
